LICENSE
MANIFEST.in
README.rst
setup.cfg
setup.py
sathub/__init__.py
sathub/api.py
sathub/custom.py
sathub/executor.py
sathub/forms.py
sathub/views.py
sathub.egg-info/PKG-INFO
sathub.egg-info/SOURCES.txt
sathub.egg-info/dependency_links.txt
sathub.egg-info/requires.txt
sathub.egg-info/top_level.txt
sathub/comum/__init__.py
sathub/comum/config.py
sathub/comum/util.py
sathub/resources/__init__.py
sathub/resources/associarassinatura.py
sathub/resources/atualizarsoftwaresat.py
sathub/resources/bloquearsat.py
sathub/resources/cancelarultimavenda.py
sathub/resources/comunicarcertificadoicpbrasil.py
sathub/resources/configurarinterfacederede.py
sathub/resources/consultarnumerosessao.py
sathub/resources/consultarsat.py
sathub/resources/consultarstatusoperacional.py
sathub/resources/desbloquearsat.py
sathub/resources/enviardadosvenda.py
sathub/resources/extrairlogs.py
sathub/resources/testefimafim.py
sathub/resources/trocarcodigodeativacao.py
sathub/static/custom.css
sathub/static/favicon.png
sathub/static/login.css
sathub/static/bootstrap-3.3.5/css/bootstrap-theme.css
sathub/static/bootstrap-3.3.5/css/bootstrap-theme.css.map
sathub/static/bootstrap-3.3.5/css/bootstrap-theme.min.css
sathub/static/bootstrap-3.3.5/css/bootstrap.css
sathub/static/bootstrap-3.3.5/css/bootstrap.css.map
sathub/static/bootstrap-3.3.5/css/bootstrap.min.css
sathub/static/bootstrap-3.3.5/fonts/glyphicons-halflings-regular.eot
sathub/static/bootstrap-3.3.5/fonts/glyphicons-halflings-regular.svg
sathub/static/bootstrap-3.3.5/fonts/glyphicons-halflings-regular.ttf
sathub/static/bootstrap-3.3.5/fonts/glyphicons-halflings-regular.woff
sathub/static/bootstrap-3.3.5/fonts/glyphicons-halflings-regular.woff2
sathub/static/bootstrap-3.3.5/js/bootstrap.js
sathub/static/bootstrap-3.3.5/js/bootstrap.min.js
sathub/static/bootstrap-3.3.5/js/ie10-viewport-bug-workaround.js
sathub/static/bootstrap-3.3.5/js/npm.js
sathub/static/jquery-1.11.3/jquery.min.js
sathub/templates/401.html
sathub/templates/404.html
sathub/templates/base-navbar.html
sathub/templates/base-no-navbar.html
sathub/templates/base.html
sathub/templates/funcao.html
sathub/templates/index.html
