Metadata-Version: 1.1
Name: sathub
Version: 0.2
Summary: Compartilhamento do equipamento SAT via RESTful API
Home-page: http://github.com/base4sistemas/sathub/
Author: Daniel Gonçalves
Author-email: daniel@base4.com.br
License: Apache Software License
Platform: any
Classifier: Development Status :: 1 - Planning
Classifier: Environment :: Other Environment
Classifier: Framework :: Flask
Classifier: Intended Audience :: Developers
Classifier: Intended Audience :: Information Technology
Classifier: License :: OSI Approved :: Apache Software License
Classifier: Natural Language :: Portuguese (Brazilian)
Classifier: Operating System :: OS Independent
Classifier: Programming Language :: Python
Classifier: Topic :: Office/Business :: Financial :: Point-Of-Sale
